viewasuser/__init__.py
viewasuser/middleware.py
viewasuser/templates/.DS_Store
viewasuser/templates/viewas/.DS_Store
viewasuser/templates/viewas/header.html
viewasuser-1.0.6.dist-info/LICENSE.txt
viewasuser-1.0.6.dist-info/METADATA
viewasuser-1.0.6.dist-info/WHEEL
viewasuser-1.0.6.dist-info/top_level.txt
viewasuser-1.0.6.dist-info/RECORD
