Metadata-Version: 2.1
Name: viewasuser
Version: 1.0.6
Summary: Django View As user is a middleware thats provides login in as any user functionality. It is modification of [django-view-as] package. The django-view-as is not supported on django 2 and newer version, so I have modified the package.
Home-page: https://github.com/raselTarikul/ViewASUser
Author: Tarikul Islam
Author-email: ti.rasel@gmail.com
License: UNKNOWN
Platform: UNKNOWN
Classifier: Programming Language :: Python :: 3
Classifier: License :: OSI Approved :: MIT License
Classifier: Operating System :: OS Independent
Requires-Python: >=2.7
